[
  {
    "conference": "Eastern Conference",
    "team": "Detroit Pistons",
    "wins": 60.0,
    "losses": 22.0,
    "seed": 1.0
  },
  {
    "conference": "Eastern Conference",
    "team": "Atlanta Hawks",
    "wins": 46.0,
    "losses": 36.0,
    "seed": 6.0
  },
  {
    "conference": "Eastern Conference",
    "team": "Boston Celtics",
    "wins": 56.0,
    "losses": 26.0,
    "seed": 2.0
  },
  {
    "conference": "Eastern Conference",
    "team": "Toronto Raptors",
    "wins": 46.0,
    "losses": 36.0,
    "seed": 5.0
  },
  {
    "conference": "Eastern Conference",
    "team": "Cleveland Cavaliers",
    "wins": 52.0,
    "losses": 30.0,
    "seed": 4.0
  },
  {
    "conference": "Eastern Conference",
    "team": "New York Knicks",
    "wins": 53.0,
    "losses": 29.0,
    "seed": 3.0
  },
  {
    "conference": "Eastern Conference",
    "team": "Miami Heat",
    "wins": 43.0,
    "losses": 39.0,
    "seed": 10.0
  },
  {
    "conference": "Eastern Conference",
    "team": "Charlotte Hornets",
    "wins": 44.0,
    "losses": 38.0,
    "seed": 9.0
  },
  {
    "conference": "Eastern Conference",
    "team": "Philadelphia 76ers",
    "wins": 45.0,
    "losses": 37.0,
    "seed": 7.0
  },
  {
    "conference": "Eastern Conference",
    "team": "Orlando Magic",
    "wins": 45.0,
    "losses": 37.0,
    "seed": 8.0
  },
  {
    "conference": "Eastern Conference",
    "team": "Washington Wizards",
    "wins": 17.0,
    "losses": 65.0,
    "seed": 15.0
  },
  {
    "conference": "Eastern Conference",
    "team": "Indiana Pacers",
    "wins": 19.0,
    "losses": 63.0,
    "seed": 14.0
  },
  {
    "conference": "Eastern Conference",
    "team": "Brooklyn Nets",
    "wins": 20.0,
    "losses": 62.0,
    "seed": 13.0
  },
  {
    "conference": "Eastern Conference",
    "team": "Chicago Bulls",
    "wins": 31.0,
    "losses": 51.0,
    "seed": 12.0
  },
  {
    "conference": "Eastern Conference",
    "team": "Milwaukee Bucks",
    "wins": 32.0,
    "losses": 50.0,
    "seed": 11.0
  },
  {
    "conference": "Western Conference",
    "team": "Los Angeles Lakers",
    "wins": 53.0,
    "losses": 29.0,
    "seed": 4.0
  },
  {
    "conference": "Western Conference",
    "team": "San Antonio Spurs",
    "wins": 62.0,
    "losses": 20.0,
    "seed": 2.0
  },
  {
    "conference": "Western Conference",
    "team": "Minnesota Timberwolves",
    "wins": 49.0,
    "losses": 33.0,
    "seed": 6.0
  },
  {
    "conference": "Western Conference",
    "team": "Houston Rockets",
    "wins": 52.0,
    "losses": 30.0,
    "seed": 5.0
  },
  {
    "conference": "Western Conference",
    "team": "Denver Nuggets",
    "wins": 54.0,
    "losses": 28.0,
    "seed": 3.0
  },
  {
    "conference": "Western Conference",
    "team": "Golden State Warriors",
    "wins": 37.0,
    "losses": 45.0,
    "seed": 10.0
  },
  {
    "conference": "Western Conference",
    "team": "Portland Trail Blazers",
    "wins": 42.0,
    "losses": 40.0,
    "seed": 8.0
  },
  {
    "conference": "Western Conference",
    "team": "LA Clippers",
    "wins": 42.0,
    "losses": 40.0,
    "seed": 9.0
  },
  {
    "conference": "Western Conference",
    "team": "Phoenix Suns",
    "wins": 45.0,
    "losses": 37.0,
    "seed": 7.0
  },
  {
    "conference": "Western Conference",
    "team": "Sacramento Kings",
    "wins": 22.0,
    "losses": 60.0,
    "seed": 14.0
  },
  {
    "conference": "Western Conference",
    "team": "Utah Jazz",
    "wins": 22.0,
    "losses": 60.0,
    "seed": 15.0
  },
  {
    "conference": "Western Conference",
    "team": "Memphis Grizzlies",
    "wins": 25.0,
    "losses": 57.0,
    "seed": 13.0
  },
  {
    "conference": "Western Conference",
    "team": "New Orleans Pelicans",
    "wins": 26.0,
    "losses": 56.0,
    "seed": 11.0
  },
  {
    "conference": "Western Conference",
    "team": "Dallas Mavericks",
    "wins": 26.0,
    "losses": 56.0,
    "seed": 12.0
  },
  {
    "conference": "Western Conference",
    "team": "Oklahoma City Thunder",
    "wins": 64.0,
    "losses": 18.0,
    "seed": 1.0
  }
]
